mars_similarity_tools/__init__.py
mars_similarity_tools/augmentation/__init__.py
mars_similarity_tools/models/__init__.py
mars_similarity_tools/services/__init__.py
mars_similarity_tools/storages/__init__.py
mars_similarity_tools-0.3.2.dist-info/METADATA
mars_similarity_tools-0.3.2.dist-info/WHEEL
mars_similarity_tools-0.3.2.dist-info/RECORD
