Metadata-Version: 2.1
Name: mars-similarity-tools
Version: 0.3.2
Summary: 
Author: znittzel
Author-email: rikard@ourstudio.se
Requires-Python: >=3.9,<4.0
Classifier: Programming Language :: Python :: 3
Classifier: Programming Language :: Python :: 3.9
Classifier: Programming Language :: Python :: 3.10
Classifier: Programming Language :: Python :: 3.11
Classifier: Programming Language :: Python :: 3.12
Requires-Dist: dill (>=0.3.8,<0.4.0)
Requires-Dist: mars-vectorizer-sdk (>=0.2.0,<0.3.0)
Requires-Dist: maz (>=0.0.12,<0.0.13)
Requires-Dist: more-itertools (>=10.2.0,<11.0.0)
Requires-Dist: numpy (>=1.26.4,<2.0.0)
